setup.py
lambda_webhook_queue.egg-info/PKG-INFO
lambda_webhook_queue.egg-info/SOURCES.txt
lambda_webhook_queue.egg-info/dependency_links.txt
lambda_webhook_queue.egg-info/entry_points.txt
lambda_webhook_queue.egg-info/not-zip-safe
lambda_webhook_queue.egg-info/requires.txt
lambda_webhook_queue.egg-info/top_level.txt
lambdawebhook/__init__.py
lambdawebhook/hook.py
lambdawebhook/sqs.py