Metadata-Version: 1.1
Name: lambda-webhook-queue
Version: 0.2.0
Summary: AWS Lambda function to receive GitHub webhooks from API gateway and relay them to an EC2 instance
Home-page: https://github.com/skruger/lambda-webhook
Author: John Schwinghammer
Author-email: john+githubsource@pristine.io
License: BSD
Platform: any
Classifier: Development Status :: 4 - Beta
Classifier: Environment :: Other Environment
Classifier: Intended Audience :: Developers
Classifier: License :: OSI Approved :: BSD License
Classifier: Operating System :: POSIX :: Linux
Classifier: Operating System :: MacOS
Classifier: Programming Language :: Python
Classifier: Programming Language :: Python :: 2
Classifier: Topic :: Software Development :: Build Tools
